{
  "modelVersion" : "2.2",
  "id" : "jobApplicationAnalysis",
  "name" : "jobApplicationAnalysis",
  "lastUpdate" : 1642282049314,
  "rows" : [
    [
      {
        "type" : "container",
        "dimension" : {
          "xs" : 12
        },
        "propertyValues" : {
          "cssClasses" : {
            "type" : "constant",
            "value" : ""
          },
          "hidden" : {
            "type" : "constant",
            "value" : false
          },
          "repeatedCollection" : {
            "type" : "variable",
            "value" : ""
          }
        },
        "reference" : "d0360e3b-e8b8-4527-a9a3-3dbccb453693",
        "hasValidationError" : false,
        "id" : "pbContainer",
        "rows" : [
          [ ]
        ]
      }
    ],
    [
      {
        "type" : "formContainer",
        "dimension" : {
          "xs" : 12
        },
        "propertyValues" : { },
        "reference" : "22b996dd-a070-461b-8630-b5b479043365",
        "hasValidationError" : false,
        "id" : "pbFormContainer",
        "container" : {
          "type" : "container",
          "dimension" : {
            "xs" : 12
          },
          "propertyValues" : { },
          "reference" : "142ae139-87ec-417b-8777-cbe29facd15a",
          "hasValidationError" : false,
          "id" : "pbContainer",
          "rows" : [
            [
              {
                "type" : "component",
                "dimension" : {
                  "md" : 12,
                  "sm" : 12,
                  "xs" : 12,
                  "lg" : 12
                },
                "propertyValues" : {
                  "hidden" : {
                    "type" : "constant",
                    "value" : false
                  },
                  "level" : {
                    "type" : "constant",
                    "value" : "Level 4"
                  },
                  "cssClasses" : {
                    "type" : "constant",
                    "value" : ""
                  },
                  "text" : {
                    "type" : "interpolation",
                    "value" : "Pending Job Application"
                  },
                  "alignment" : {
                    "type" : "constant",
                    "value" : "left"
                  },
                  "dimension" : {
                    "type" : "constant",
                    "value" : 12
                  }
                },
                "reference" : "19740c0b-f2ae-4698-83fa-d23c490bcdbb",
                "hasValidationError" : false,
                "id" : "pbTitle",
                "description" : ""
              }
            ],
            [
              {
                "type" : "container",
                "dimension" : {
                  "md" : 12,
                  "sm" : 12,
                  "xs" : 12,
                  "lg" : 12
                },
                "propertyValues" : {
                  "repeatedCollection" : {
                    "type" : "variable",
                    "value" : ""
                  },
                  "hidden" : {
                    "type" : "constant",
                    "value" : false
                  },
                  "cssClasses" : {
                    "type" : "constant",
                    "value" : ""
                  },
                  "dimension" : {
                    "type" : "constant",
                    "value" : 12
                  }
                },
                "reference" : "0f9e80f0-ca2b-48e4-8e9d-14f7eaa5d230",
                "hasValidationError" : false,
                "id" : "pbContainer",
                "rows" : [
                  [
                    {
                      "type" : "component",
                      "dimension" : {
                        "md" : 6,
                        "sm" : 12,
                        "xs" : 12,
                        "lg" : 6
                      },
                      "propertyValues" : {
                        "cssClasses" : {
                          "type" : "constant",
                          "value" : ""
                        },
                        "hidden" : {
                          "type" : "expression",
                          "value" : "!jobApplication.name"
                        },
                        "labelHidden" : {
                          "type" : "constant",
                          "value" : false
                        },
                        "label" : {
                          "type" : "interpolation",
                          "value" : "Name"
                        },
                        "labelPosition" : {
                          "type" : "constant",
                          "value" : "top"
                        },
                        "labelWidth" : {
                          "type" : "constant",
                          "value" : 1
                        },
                        "allowHTML" : {
                          "type" : "constant",
                          "value" : true
                        },
                        "text" : {
                          "type" : "interpolation",
                          "value" : "{{jobApplication.name}}"
                        },
                        "alignment" : {
                          "type" : "constant",
                          "value" : "left"
                        }
                      },
                      "reference" : "a9d7f5f3-09eb-4898-854d-c74f1f2aba43",
                      "hasValidationError" : false,
                      "id" : "pbText"
                    },
                    {
                      "type" : "component",
                      "dimension" : {
                        "md" : 6,
                        "sm" : 12,
                        "xs" : 12,
                        "lg" : 6
                      },
                      "propertyValues" : {
                        "allowHtml" : {
                          "type" : "constant",
                          "value" : true
                        },
                        "labelHidden" : {
                          "type" : "constant",
                          "value" : false
                        },
                        "hidden" : {
                          "type" : "expression",
                          "value" : "!jobApplication.lastName"
                        },
                        "cssClasses" : {
                          "type" : "constant",
                          "value" : ""
                        },
                        "label" : {
                          "type" : "interpolation",
                          "value" : "Last Name"
                        },
                        "text" : {
                          "type" : "interpolation",
                          "value" : "{{jobApplication.lastName}}"
                        },
                        "alignment" : {
                          "type" : "constant",
                          "value" : "left"
                        },
                        "dimension" : {
                          "type" : "constant",
                          "value" : 12
                        },
                        "labelPosition" : {
                          "type" : "constant",
                          "value" : "top"
                        },
                        "labelWidth" : {
                          "type" : "constant",
                          "value" : 4
                        },
                        "allowHTML" : {
                          "type" : "constant",
                          "value" : true
                        }
                      },
                      "reference" : "34fd1720-ff4e-4a9b-a100-24873c2ac2b5",
                      "hasValidationError" : false,
                      "id" : "pbText",
                      "description" : ""
                    }
                  ],
                  [
                    {
                      "type" : "component",
                      "dimension" : {
                        "md" : 6,
                        "sm" : 12,
                        "xs" : 12,
                        "lg" : 6
                      },
                      "propertyValues" : {
                        "allowHtml" : {
                          "type" : "constant",
                          "value" : true
                        },
                        "labelHidden" : {
                          "type" : "constant",
                          "value" : false
                        },
                        "hidden" : {
                          "type" : "expression",
                          "value" : "!jobApplication.email"
                        },
                        "cssClasses" : {
                          "type" : "constant",
                          "value" : ""
                        },
                        "label" : {
                          "type" : "interpolation",
                          "value" : "Email"
                        },
                        "text" : {
                          "type" : "interpolation",
                          "value" : "{{jobApplication.email}}"
                        },
                        "alignment" : {
                          "type" : "constant",
                          "value" : "left"
                        },
                        "dimension" : {
                          "type" : "constant",
                          "value" : 12
                        },
                        "labelPosition" : {
                          "type" : "constant",
                          "value" : "top"
                        },
                        "labelWidth" : {
                          "type" : "constant",
                          "value" : 4
                        },
                        "allowHTML" : {
                          "type" : "constant",
                          "value" : true
                        }
                      },
                      "reference" : "449cb1bb-1f9a-44b2-b8ff-97069609e7d0",
                      "hasValidationError" : false,
                      "id" : "pbText",
                      "description" : ""
                    },
                    {
                      "type" : "component",
                      "dimension" : {
                        "md" : 6,
                        "sm" : 12,
                        "xs" : 12,
                        "lg" : 6
                      },
                      "propertyValues" : {
                        "allowHtml" : {
                          "type" : "constant",
                          "value" : true
                        },
                        "labelHidden" : {
                          "type" : "constant",
                          "value" : false
                        },
                        "hidden" : {
                          "type" : "expression",
                          "value" : "!jobApplication.address"
                        },
                        "cssClasses" : {
                          "type" : "constant",
                          "value" : ""
                        },
                        "label" : {
                          "type" : "interpolation",
                          "value" : "Address"
                        },
                        "text" : {
                          "type" : "interpolation",
                          "value" : "{{jobApplication.address}}"
                        },
                        "alignment" : {
                          "type" : "constant",
                          "value" : "left"
                        },
                        "dimension" : {
                          "type" : "constant",
                          "value" : 12
                        },
                        "labelPosition" : {
                          "type" : "constant",
                          "value" : "top"
                        },
                        "labelWidth" : {
                          "type" : "constant",
                          "value" : 4
                        },
                        "allowHTML" : {
                          "type" : "constant",
                          "value" : true
                        }
                      },
                      "reference" : "b95a867f-a27e-4871-8fc8-ea5eea445bad",
                      "hasValidationError" : false,
                      "id" : "pbText",
                      "description" : ""
                    }
                  ],
                  [
                    {
                      "type" : "container",
                      "dimension" : {
                        "md" : 12,
                        "sm" : 12,
                        "xs" : 12,
                        "lg" : 12
                      },
                      "propertyValues" : {
                        "repeatedCollection" : {
                          "type" : "variable"
                        },
                        "hidden" : {
                          "type" : "constant",
                          "value" : false
                        },
                        "cssClasses" : {
                          "type" : "constant",
                          "value" : ""
                        },
                        "dimension" : {
                          "type" : "constant",
                          "value" : 12
                        }
                      },
                      "reference" : "a24d1520-d2de-4379-9d84-3ae556361197",
                      "hasValidationError" : false,
                      "id" : "pbContainer",
                      "rows" : [
                        [
                          {
                            "type" : "component",
                            "dimension" : {
                              "md" : 12,
                              "sm" : 12,
                              "xs" : 12,
                              "lg" : 12
                            },
                            "propertyValues" : {
                              "allowHtml" : {
                                "type" : "constant",
                                "value" : true
                              },
                              "labelHidden" : {
                                "type" : "constant",
                                "value" : false
                              },
                              "hidden" : {
                                "type" : "expression",
                                "value" : "!jobApplication.educationLevel.educationLevelName"
                              },
                              "cssClasses" : {
                                "type" : "constant",
                                "value" : ""
                              },
                              "label" : {
                                "type" : "interpolation",
                                "value" : "Education Level Name"
                              },
                              "text" : {
                                "type" : "interpolation",
                                "value" : "{{jobApplication.educationLevel.educationLevelName}}"
                              },
                              "alignment" : {
                                "type" : "constant",
                                "value" : "left"
                              },
                              "dimension" : {
                                "type" : "constant",
                                "value" : 12
                              }
                            },
                            "reference" : "4e3c09b3-60e8-4649-815a-df8748412e11",
                            "hasValidationError" : false,
                            "id" : "pbText",
                            "description" : ""
                          }
                        ]
                      ]
                    }
                  ],
                  [
                    {
                      "type" : "component",
                      "dimension" : {
                        "md" : 12,
                        "sm" : 12,
                        "xs" : 12,
                        "lg" : 12
                      },
                      "propertyValues" : {
                        "hidden" : {
                          "type" : "constant",
                          "value" : false
                        },
                        "level" : {
                          "type" : "constant",
                          "value" : "Level 4"
                        },
                        "cssClasses" : {
                          "type" : "constant",
                          "value" : ""
                        },
                        "text" : {
                          "type" : "interpolation",
                          "value" : "Job"
                        },
                        "alignment" : {
                          "type" : "constant",
                          "value" : "left"
                        },
                        "dimension" : {
                          "type" : "constant",
                          "value" : 12
                        }
                      },
                      "reference" : "0ab761b0-1164-40d8-ab78-0febdf33e99b",
                      "hasValidationError" : false,
                      "id" : "pbTitle",
                      "description" : ""
                    }
                  ],
                  [
                    {
                      "type" : "container",
                      "dimension" : {
                        "md" : 12,
                        "sm" : 12,
                        "xs" : 12,
                        "lg" : 12
                      },
                      "propertyValues" : {
                        "repeatedCollection" : {
                          "type" : "variable"
                        },
                        "hidden" : {
                          "type" : "constant",
                          "value" : false
                        },
                        "cssClasses" : {
                          "type" : "constant",
                          "value" : ""
                        },
                        "dimension" : {
                          "type" : "constant",
                          "value" : 12
                        }
                      },
                      "reference" : "5b9bb9b7-28f3-4cab-8e76-7585377556c3",
                      "hasValidationError" : false,
                      "id" : "pbContainer",
                      "rows" : [
                        [
                          {
                            "type" : "component",
                            "dimension" : {
                              "md" : 12,
                              "sm" : 12,
                              "xs" : 12,
                              "lg" : 12
                            },
                            "propertyValues" : {
                              "allowHtml" : {
                                "type" : "constant",
                                "value" : true
                              },
                              "labelHidden" : {
                                "type" : "constant",
                                "value" : false
                              },
                              "hidden" : {
                                "type" : "expression",
                                "value" : "!jobApplication_job.jobTitle"
                              },
                              "cssClasses" : {
                                "type" : "constant",
                                "value" : ""
                              },
                              "label" : {
                                "type" : "interpolation",
                                "value" : "Job Title"
                              },
                              "text" : {
                                "type" : "interpolation",
                                "value" : "{{jobApplication_job.jobTitle}}"
                              },
                              "alignment" : {
                                "type" : "constant",
                                "value" : "left"
                              },
                              "dimension" : {
                                "type" : "constant",
                                "value" : 12
                              }
                            },
                            "reference" : "26f6cea8-a9aa-4204-beb9-f5c28fd35e53",
                            "hasValidationError" : false,
                            "id" : "pbText",
                            "description" : ""
                          }
                        ],
                        [
                          {
                            "type" : "component",
                            "dimension" : {
                              "md" : 12,
                              "sm" : 12,
                              "xs" : 12,
                              "lg" : 12
                            },
                            "propertyValues" : {
                              "allowHtml" : {
                                "type" : "constant",
                                "value" : true
                              },
                              "labelHidden" : {
                                "type" : "constant",
                                "value" : false
                              },
                              "hidden" : {
                                "type" : "expression",
                                "value" : "!jobApplication_job.jobDescription"
                              },
                              "cssClasses" : {
                                "type" : "constant",
                                "value" : ""
                              },
                              "label" : {
                                "type" : "interpolation",
                                "value" : "Job Description"
                              },
                              "text" : {
                                "type" : "interpolation",
                                "value" : "{{jobApplication_job.jobDescription}}"
                              },
                              "alignment" : {
                                "type" : "constant",
                                "value" : "left"
                              },
                              "dimension" : {
                                "type" : "constant",
                                "value" : 12
                              }
                            },
                            "reference" : "91642ffa-b26f-424c-95db-6fced2fe1281",
                            "hasValidationError" : false,
                            "id" : "pbText",
                            "description" : ""
                          }
                        ]
                      ]
                    }
                  ]
                ]
              }
            ],
            [
              {
                "type" : "component",
                "dimension" : {
                  "md" : 6,
                  "sm" : 12,
                  "xs" : 12,
                  "lg" : 6
                },
                "propertyValues" : {
                  "labelHidden" : {
                    "type" : "constant",
                    "value" : false
                  },
                  "hidden" : {
                    "type" : "constant",
                    "value" : false
                  },
                  "cssClasses" : {
                    "type" : "constant",
                    "value" : ""
                  },
                  "disabled" : {
                    "type" : "constant",
                    "value" : false
                  },
                  "label" : {
                    "type" : "interpolation",
                    "value" : "Approve Job Application?"
                  },
                  "dimension" : {
                    "type" : "constant",
                    "value" : 12
                  },
                  "value" : {
                    "type" : "variable",
                    "value" : "formInput.isJobApplicationApprovedInput"
                  },
                  "required" : {
                    "type" : "constant",
                    "value" : false
                  }
                },
                "reference" : "fec12301-5c07-4202-821c-c9580bcce0c6",
                "hasValidationError" : false,
                "id" : "pbCheckbox",
                "description" : ""
              },
              {
                "type" : "component",
                "dimension" : {
                  "md" : 6,
                  "sm" : 12,
                  "xs" : 12,
                  "lg" : 6
                },
                "propertyValues" : {
                  "removeItem" : {
                    "type" : "variable"
                  },
                  "hidden" : {
                    "type" : "constant",
                    "value" : false
                  },
                  "cssClasses" : {
                    "type" : "constant",
                    "value" : ""
                  },
                  "buttonStyle" : {
                    "type" : "constant",
                    "value" : "primary"
                  },
                  "label" : {
                    "type" : "interpolation",
                    "value" : "Submit"
                  },
                  "dataToSend" : {
                    "type" : "expression",
                    "value" : "formOutput"
                  },
                  "dataFromError" : {
                    "type" : "variable",
                    "value" : "formOutput._submitError"
                  },
                  "labelHidden" : {
                    "type" : "constant",
                    "value" : false
                  },
                  "collectionPosition" : {
                    "type" : "constant"
                  },
                  "targetUrlOnSuccess" : {
                    "type" : "interpolation",
                    "value" : "/bonita"
                  },
                  "action" : {
                    "type" : "constant",
                    "value" : "Submit task"
                  },
                  "collectionToModify" : {
                    "type" : "variable"
                  },
                  "valueToAdd" : {
                    "type" : "expression"
                  },
                  "disabled" : {
                    "type" : "expression",
                    "value" : "$form.$invalid"
                  },
                  "alignment" : {
                    "type" : "constant",
                    "value" : "center"
                  },
                  "dimension" : {
                    "type" : "constant",
                    "value" : 12
                  }
                },
                "reference" : "36533102-a6c2-496c-b97b-5bb036adeb26",
                "hasValidationError" : false,
                "id" : "pbButton",
                "description" : ""
              }
            ],
            [
              {
                "type" : "component",
                "dimension" : {
                  "md" : 12,
                  "sm" : 12,
                  "xs" : 12,
                  "lg" : 12
                },
                "propertyValues" : {
                  "allowHTML" : {
                    "type" : "constant",
                    "value" : true
                  },
                  "allowHtml" : {
                    "type" : "constant",
                    "value" : true
                  },
                  "labelHidden" : {
                    "type" : "constant",
                    "value" : true
                  },
                  "hidden" : {
                    "type" : "expression",
                    "value" : "!formOutput._submitError.message"
                  },
                  "cssClasses" : {
                    "type" : "constant",
                    "value" : "alert alert-danger col-lg-6 col-lg-offset-3"
                  },
                  "label" : {
                    "type" : "interpolation"
                  },
                  "text" : {
                    "type" : "interpolation",
                    "value" : "<strong>Debug message</strong>\n<br/>\n{{formOutput._submitError.message}}\n{{submit_errors_list}}"
                  },
                  "alignment" : {
                    "type" : "constant",
                    "value" : "left"
                  },
                  "dimension" : {
                    "type" : "constant",
                    "value" : 12
                  }
                },
                "reference" : "0796a388-d557-4b21-9387-102fabe37950",
                "hasValidationError" : false,
                "id" : "pbText",
                "description" : ""
              }
            ]
          ]
        }
      }
    ]
  ],
  "assets" : [
    {
      "id" : "0d3c62bd-99d5-40b6-8cc9-42fba2e61ff4",
      "name" : "localization.json",
      "type" : "json",
      "order" : 0,
      "external" : false
    },
    {
      "id" : "33d14fc2-ae2a-46b1-915b-68f8e694dc8b",
      "name" : "style.css",
      "type" : "css",
      "order" : 0,
      "external" : false
    }
  ],
  "inactiveAssets" : [ ],
  "variables" : {
    "task" : {
      "type" : "url",
      "value" : [
        "../API/bpm/userTask/{{taskId}}"
      ],
      "exposed" : false
    },
    "formInput" : {
      "type" : "json",
      "value" : [
        "{\r",
        "  \"isJobApplicationApprovedInput\" : false\r",
        "}"
      ],
      "exposed" : false
    },
    "submit_errors_list" : {
      "type" : "expression",
      "value" : [
        "if($data.formOutput && $data.formOutput._submitError && $data.formOutput._submitError.explanations){",
        "\tconst liElements = $data.formOutput._submitError.explanations",
        "\t\t.filter(cause => cause !== null)",
        "\t\t.map(cause => \"<li>\" + cause + \"</li>\")",
        "\t\t.join('');",
        "\tif(liElements){",
        "\t\treturn \"<ul>\" + liElements + \"</ul>\";",
        "\t}",
        "}"
      ],
      "exposed" : false
    },
    "formOutput" : {
      "type" : "expression",
      "value" : [
        "if( $data.jobApplication && $data.jobApplication_job ){",
        "\t//attach lazy references variables to parent variables",
        "\t$data.jobApplication.job = $data.jobApplication_job;",
        "\treturn {",
        "\t\tisJobApplicationApprovedInput: $data.formInput.isJobApplicationApprovedInput,",
        "\t\t//map jobApplication variable to expected task contract input",
        "\t\tjobApplicationInput: {",
        "\t\t\tname: $data.jobApplication.name !== undefined ? $data.jobApplication.name : null",
        "\t\t}",
        "\t}",
        "}"
      ],
      "exposed" : false
    },
    "jobApplication" : {
      "type" : "url",
      "value" : [
        "../{{context.jobApplication_ref.link}}"
      ],
      "exposed" : false
    },
    "jobApplication_job" : {
      "type" : "url",
      "value" : [
        "{{jobApplication|lazyRef:'job'}}"
      ],
      "exposed" : false
    },
    "context" : {
      "type" : "url",
      "value" : [
        "../API/bpm/userTask/{{taskId}}/context"
      ],
      "exposed" : false
    },
    "taskId" : {
      "type" : "urlparameter",
      "value" : [
        "id"
      ],
      "exposed" : false
    }
  },
  "hasValidationError" : false,
  "uuid" : "f181ad8b-54f9-4303-8d85-9fd063e9aca8",
  "type" : "form",
  "description" : "Page generated with Bonita UI designer"
}